minex/__init__.py
minex/backend/__init__.py
minex/backend/audio_player.py
minex/backend/game_engine.py
minex/backend/game_settings.py
minex/backend/game_statistics.py
minex/backend/theme_manager.py
minex/config.py
minex/constants.py
minex/frontend/custom_widgets/select_button.py
minex/frontend/custom_widgets/time_display.py
minex/frontend/custom_widgets/toggle_button.py
minex/frontend/screens/custom_board.py
minex/frontend/screens/option_overlay.py
minex/frontend/themes/__init__.py
minex/frontend/themes/cyberpunk_theme.py
minex/frontend/themes/default_theme.py
minex/frontend/themes/desert_theme.py
minex/frontend/themes/space_theme.py
minex/frontend/themes/winter_theme.py
minex/frontend/views/board.py
minex/frontend/views/cell.py
minex/frontend/views/footer.py
minex/frontend/views/header.py
minex/game_events.py
minex/main.py
minex/sounds/big_move.mp3
minex/sounds/button.mp3
minex/sounds/chording.mp3
minex/sounds/flag.mp3
minex/sounds/game_lost.mp3
minex/sounds/game_won.mp3
minex/sounds/new_level.mp3
minex/sounds/tile_revealed.mp3
minex/sounds/toggle.mp3
minex-1.0.0.dist-info/entry_points.txt
minex-1.0.0.dist-info/LICENCE
minex-1.0.0.dist-info/METADATA
minex-1.0.0.dist-info/WHEEL
minex-1.0.0.dist-info/RECORD
