Metadata-Version: 2.3
Name: minex
Version: 1.0.0
Summary: AESTHETIC TERMINAL BASED MINESWEEPER GAME THAT SUPPORTS MOUSE CLICKS FOR GAMEPLAY
License: MIT
Author: Libin Lalu
Author-email: libinlalu000@gmail.com
Requires-Python: >=3.9,<4.0.0
Classifier: License :: OSI Approved :: MIT License
Classifier: Programming Language :: Python :: 3
Classifier: Programming Language :: Python :: 3.9
Classifier: Programming Language :: Python :: 3.10
Classifier: Programming Language :: Python :: 3.11
Classifier: Programming Language :: Python :: 3.12
Classifier: Programming Language :: Python :: 3.13
Requires-Dist: pygame (>=2.6.1,<3.0.0)
Requires-Dist: textual (==1.0.0)
